appligen/__init__.py
appligen/admin.py
appligen/apps.py
appligen/cli.py
appligen/generator.py
appligen/models.py
appligen/run.py
appligen/tests.py
appligen/views.py
appligen/migrations/__init__.py
envgen/__init__.py
envgen/admin.py
envgen/apps.py
envgen/cli.py
envgen/models.py
envgen/tests.py
envgen/views.py
envgen/migrations/__init__.py
appligen-0.3.2.dist-info/METADATA
appligen-0.3.2.dist-info/WHEEL
appligen-0.3.2.dist-info/entry_points.txt
appligen-0.3.2.dist-info/top_level.txt
appligen-0.3.2.dist-info/RECORD
